<keymap version="1" name="MY OWN" parent="$default">
  <action id="$Redo">
    <keyboard-shortcut first-keystroke="shift ctrl z" />
    <keyboard-shortcut first-keystroke="shift alt back_space" />
    <keyboard-shortcut first-keystroke="ctrl y" />
  </action>
  <action id="CloseActiveTab">
    <keyboard-shortcut first-keystroke="shift ctrl f4" />
    <keyboard-shortcut first-keystroke="ctrl w" />
  </action>
  <action id="CloseAllEditors">
    <keyboard-shortcut first-keystroke="shift ctrl w" />
  </action>
  <action id="CloseAllEditorsButActive">
    <keyboard-shortcut first-keystroke="ctrl alt w" />
  </action>
  <action id="CloseContent">
    <keyboard-shortcut first-keystroke="ctrl f4" />
    <keyboard-shortcut first-keystroke="ctrl w" />
  </action>
  <action id="DecrementWindowHeight" />
  <action id="Editor Redo">
    <keyboard-shortcut first-keystroke="ctrl y" />
  </action>
  <action id="EditorDeleteLine">
    <keyboard-shortcut first-keystroke="ctrl d" />
  </action>
  <action id="EditorDuplicate">
    <keyboard-shortcut first-keystroke="alt d" />
  </action>
  <action id="EditorLineEnd">
    <keyboard-shortcut first-keystroke="end" />
    <keyboard-shortcut first-keystroke="f13" second-keystroke="right" />
  </action>
  <action id="EditorLineEndWithSelection">
    <keyboard-shortcut first-keystroke="shift end" />
    <keyboard-shortcut first-keystroke="shift f13" second-keystroke="right" />
  </action>
  <action id="EditorLineStart">
    <keyboard-shortcut first-keystroke="home" />
    <keyboard-shortcut first-keystroke="f13" second-keystroke="left" />
  </action>
  <action id="EditorLineStartWithSelection">
    <keyboard-shortcut first-keystroke="shift home" />
    <keyboard-shortcut first-keystroke="shift f13" second-keystroke="left" />
  </action>
  <action id="EditorSelectWord">
    <keyboard-shortcut first-keystroke="shift ctrl up" />
  </action>
  <action id="EditorUnSelectWord">
    <keyboard-shortcut first-keystroke="shift ctrl down" />
  </action>
  <action id="IncrementWindowHeight" />
  <action id="Kotlin.RunScratch" />
  <action id="MoveStatementDown">
    <keyboard-shortcut first-keystroke="ctrl alt down" />
  </action>
  <action id="MoveStatementUp">
    <keyboard-shortcut first-keystroke="ctrl alt up" />
  </action>
  <action id="RenameElement">
    <keyboard-shortcut first-keystroke="shift f6" />
    <keyboard-shortcut first-keystroke="shift alt r" />
  </action>
  <action id="RerunTests" />
  <action id="ResetColumnsWidth" />
  <action id="ResizeToolWindowDown" />
  <action id="ResizeToolWindowUp" />
</keymap>